very_plot/__init__.py
very_plot/themes.py
very_plot-0.4.2.dist-info/LICENSE
very_plot-0.4.2.dist-info/WHEEL
very_plot-0.4.2.dist-info/METADATA
very_plot-0.4.2.dist-info/RECORD
